Metadata-Version: 2.1
Name: localstack-obfuscator
Version: 0.3.0
Summary: Obfuscate proprietary LocalStack code bases
Author-email: LocalStack Contributors <info@localstack.cloud>
License: Proprietary
Classifier: Operating System :: OS Independent
Classifier: Programming Language :: Python :: 3
Classifier: Programming Language :: Python :: 3.10
Classifier: Programming Language :: Python :: 3.11
Classifier: Programming Language :: Python :: 3.12
Requires-Python: >=3.10
Requires-Dist: python-minifier==2.9.0
Requires-Dist: PyYAML
Provides-Extra: dev
Requires-Dist: ruff>=0.5.2; extra == "dev"
